discord_booster/__init__.py
discord_booster/booster.py
alpha_booster-1.3.dist-info/METADATA
alpha_booster-1.3.dist-info/WHEEL
alpha_booster-1.3.dist-info/entry_points.txt
alpha_booster-1.3.dist-info/top_level.txt
alpha_booster-1.3.dist-info/RECORD
