Metadata-Version: 2.4
Name: alpha-booster
Version: 1.3
Requires-Dist: requests
Requires-Dist: colorama
Dynamic: requires-dist
